assets/highlight.js/.git
assets/highlight.js/.gitignore
assets/highlight.js/DIGESTS.md
assets/highlight.js/LICENSE
assets/highlight.js/README.md
assets/highlight.js/build/LICENSE
assets/highlight.js/build/README.md
assets/highlight.js/build/es/core.js
assets/highlight.js/build/es/core.min.js
assets/highlight.js/build/es/highlight.js
assets/highlight.js/build/es/highlight.min.js
assets/highlight.js/build/es/languages/1c.min.js
assets/highlight.js/build/es/languages/abnf.min.js
assets/highlight.js/build/es/languages/accesslog.min.js
assets/highlight.js/build/es/languages/actionscript.min.js
assets/highlight.js/build/es/languages/ada.min.js
assets/highlight.js/build/es/languages/angelscript.min.js
assets/highlight.js/build/es/languages/apache.min.js
assets/highlight.js/build/es/languages/applescript.min.js
assets/highlight.js/build/es/languages/arcade.min.js
assets/highlight.js/build/es/languages/arduino.min.js
assets/highlight.js/build/es/languages/armasm.min.js
assets/highlight.js/build/es/languages/asciidoc.min.js
assets/highlight.js/build/es/languages/aspectj.min.js
assets/highlight.js/build/es/languages/autohotkey.min.js
assets/highlight.js/build/es/languages/autoit.min.js
assets/highlight.js/build/es/languages/avrasm.min.js
assets/highlight.js/build/es/languages/awk.min.js
assets/highlight.js/build/es/languages/axapta.min.js
assets/highlight.js/build/es/languages/bash.min.js
assets/highlight.js/build/es/languages/basic.min.js
assets/highlight.js/build/es/languages/bnf.min.js
assets/highlight.js/build/es/languages/brainfuck.min.js
assets/highlight.js/build/es/languages/c.min.js
assets/highlight.js/build/es/languages/cal.min.js
assets/highlight.js/build/es/languages/capnproto.min.js
assets/highlight.js/build/es/languages/ceylon.min.js
assets/highlight.js/build/es/languages/clean.min.js
assets/highlight.js/build/es/languages/clojure-repl.min.js
assets/highlight.js/build/es/languages/clojure.min.js
assets/highlight.js/build/es/languages/cmake.min.js
mkslides_reveal-0.1.25.dist-info/LICENSE
mkslides_reveal-0.1.25.dist-info/METADATA
mkslides_reveal-0.1.25.dist-info/WHEEL
mkslides_reveal-0.1.25.dist-info/entry_points.txt
mkslides_reveal-0.1.25.dist-info/RECORD
