Metadata-Version: 2.1
Name: mkslides-reveal
Version: 0.1.25
Summary: MkSlides-Reveal - Slides with Markdown using the power of Reveal.js.
Home-page: https://github.com/MartenBE/mkslides-reveal
License: MIT
Author: MartenBE
Requires-Python: >=3.12,<4.0
Classifier: License :: OSI Approved :: MIT License
Classifier: Programming Language :: Python :: 3
Classifier: Programming Language :: Python :: 3.12
Requires-Dist: Jinja2 (>=3.1.4,<4.0.0)
Requires-Dist: PyYAML (>=6.0.2,<7.0.0)
Requires-Dist: click (>=8.1.7,<9.0.0)
Requires-Dist: emoji (>=2.12.1,<3.0.0)
Requires-Dist: jsonschema (>=4.23.0,<5.0.0)
Requires-Dist: livereload (>=2.7.0,<3.0.0)
Requires-Dist: natsort (>=8.4.0,<9.0.0)
Requires-Dist: python-frontmatter (>=1.1.0,<2.0.0)
Requires-Dist: rich (>=13.8.0,<14.0.0)
Project-URL: Repository, https://github.com/MartenBE/mkslides-reveal
